{
    "name": "nos.AI.ModelNodes",
    "releases": [
        {
            "version": "2.0.0.b163",
            "url": "https://github.com/mediaz/modules-releases/releases/download/nos.AI.ModelNodes-2.0.0.b163/nos.AI.ModelNodes-2.0.0.b163.zip"
        },
        {
            "version": "2.0.0.b107",
            "url": "https://github.com/mediaz/modules-releases/releases/download/nos.AI.ModelNodes-2.0.0.b107/nos.AI.ModelNodes-2.0.0.b107.zip"
        },
        {
            "version": "2.0.0.b105",
            "url": "https://github.com/mediaz/modules-releases/releases/download/nos.AI.ModelNodes-2.0.0.b105/nos.AI.ModelNodes-2.0.0.b105.zip"
        },
        {
            "version": "2.0.0.b103",
            "url": "https://github.com/mediaz/modules-releases/releases/download/nos.AI.ModelNodes-2.0.0.b103/nos.AI.ModelNodes-2.0.0.b103.zip"
        },
        {
            "version": "1.0.0.b96",
            "url": "https://github.com/mediaz/modules-releases/releases/download/nos.AI.ModelNodes-1.0.0.b96/nos.AI.ModelNodes-1.0.0.b96.zip"
        },
        {
            "version": "1.0.0.b95",
            "url": "https://github.com/mediaz/modules-releases/releases/download/nos.AI.ModelNodes-1.0.0.b95/nos.AI.ModelNodes-1.0.0.b95.zip"
        },
        {
            "version": "1.0.0.b94",
            "url": "https://github.com/mediaz/modules-releases/releases/download/nos.AI.ModelNodes-1.0.0.b94/nos.AI.ModelNodes-1.0.0.b94.zip"
        },
        {
            "version": "1.0.0.b93",
            "url": "https://github.com/mediaz/modules-releases/releases/download/nos.AI.ModelNodes-1.0.0.b93/nos.AI.ModelNodes-1.0.0.b93.zip"
        },
        {
            "version": "1.0.0.b90",
            "url": "https://github.com/mediaz/modules-releases/releases/download/nos.AI.ModelNodes-1.0.0.b90/nos.AI.ModelNodes-1.0.0.b90.zip"
        },
        {
            "version": "1.0.0.b88",
            "url": "https://github.com/mediaz/modules-releases/releases/download/nos.AI.ModelNodes-1.0.0.b88/nos.AI.ModelNodes-1.0.0.b88.zip"
        },
        {
            "version": "1.0.0.b81",
            "url": "https://github.com/mediaz/modules-releases/releases/download/nos.AI.ModelNodes-1.0.0.b81/nos.AI.ModelNodes-1.0.0.b81.zip"
        }
    ]
}